aiowialon/__init__.py
aiowialon/_version.py
aiowialon/api.py
aiowialon/api.pyi
aiowialon/exceptions.py
aiowialon/logger.py
aiowialon/shortcuts/__init__.py
aiowialon/shortcuts/wlp.py
aiowialon/types/__init__.py
aiowialon/types/avl_events.py
aiowialon/types/flags.py
aiowialon/types/login.py
aiowialon/types/multipart.py
aiowialon/utils/__init__.py
aiowialon/utils/async_lock.py
aiowialon/utils/compat.py
aiowialon/utils/convention.py
aiowialon/validators/__init__.py
aiowialon/validators/call_validator.py
py_aiowialon-1.3.5.dist-info/METADATA
py_aiowialon-1.3.5.dist-info/WHEEL
py_aiowialon-1.3.5.dist-info/top_level.txt
py_aiowialon-1.3.5.dist-info/RECORD
