Metadata-Version: 2.4
Name: py-aiowialon
Version: 1.3.5
Summary: Async Wialon Remote API wrapper for Python 3
Author-email: o-murphy <thehelixpg@gmail.com>
License: MIT License
Project-URL: Homepage, https://github.com/o-murphy/py-aiowialon
Project-URL: Bug Reports, https://github.com/o-murphy/py-aiowialon/issues
Project-URL: Source, https://github.com/o-murphy/py-aiowialon
Keywords: asyncio,wialon,wialon remote api,gurtam
Classifier: Intended Audience :: Developers
Classifier: Natural Language :: English
Classifier: Programming Language :: Python
Classifier: Topic :: Software Development :: Libraries :: Python Modules
Classifier: Programming Language :: Python :: 3
Classifier: Programming Language :: Python :: 3 :: Only
Classifier: Programming Language :: Python :: 3.8
Classifier: Programming Language :: Python :: 3.9
Classifier: Programming Language :: Python :: 3.10
Classifier: Programming Language :: Python :: 3.11
Classifier: Programming Language :: Python :: 3.12
Classifier: Operating System :: OS Independent
Classifier: Programming Language :: Python :: Implementation :: CPython
Requires-Python: >=3.8
Requires-Dist: aiohttp
Requires-Dist: aiolimiter
Requires-Dist: strenum; python_version < "3.11"
Provides-Extra: dev
Requires-Dist: mypy; extra == "dev"
Requires-Dist: pylint; extra == "dev"
Requires-Dist: pytest; extra == "dev"
Requires-Dist: build; extra == "dev"
